[
  {
    "inputs": [
      {
        "internalType": "address",
        "name": "hubAddress",
        "type": "address"
      }
    ],
    "stateMutability": "nonpayable",
    "type": "constructor"
  },
  {
    "anonymous": false,
    "inputs": [
      {
        "indexed": true,
        "internalType": "bytes32",
        "name": "assertionId",
        "type": "bytes32"
      },
      {
        "indexed": false,
        "internalType": "uint128",
        "name": "size",
        "type": "uint128"
      },
      {
        "indexed": false,
        "internalType": "uint32",
        "name": "triplesNumber",
        "type": "uint32"
      },
      {
        "indexed": false,
        "internalType": "uint96",
        "name": "chunksNumber",
        "type": "uint96"
      }
    ],
    "name": "AssertionCreated",
    "type": "event"
  },
  {
    "inputs": [],
    "name": "assertionStorage",
    "outputs": [
      {
        "internalType": "contract AssertionStorage",
        "name": "",
        "type": "address"
      }
    ],
    "stateMutability": "view",
    "type": "function"
  },
  {
    "inputs": [
      {
        "internalType": "bytes32",
        "name": "assertionId",
        "type": "bytes32"
      },
      {
        "internalType": "uint128",
        "name": "size",
        "type": "uint128"
      },
      {
        "internalType": "uint32",
        "name": "triplesNumber",
        "type": "uint32"
      },
      {
        "internalType": "uint96",
        "name": "chunksNumber",
        "type": "uint96"
      }
    ],
    "name": "createAssertion",
    "outputs": [],
    "stateMutability": "nonpayable",
    "type": "function"
  },
  {
    "inputs": [],
    "name": "hub",
    "outputs": [
      {
        "internalType": "contract Hub",
        "name": "",
        "type": "address"
      }
    ],
    "stateMutability": "view",
    "type": "function"
  },
  {
    "inputs": [],
    "name": "initialize",
    "outputs": [],
    "stateMutability": "nonpayable",
    "type": "function"
  },
  {
    "inputs": [],
    "name": "name",
    "outputs": [
      {
        "internalType": "string",
        "name": "",
        "type": "string"
      }
    ],
    "stateMutability": "pure",
    "type": "function"
  },
  {
    "inputs": [
      {
        "internalType": "bool",
        "name": "_status",
        "type": "bool"
      }
    ],
    "name": "setStatus",
    "outputs": [],
    "stateMutability": "nonpayable",
    "type": "function"
  },
  {
    "inputs": [],
    "name": "status",
    "outputs": [
      {
        "internalType": "bool",
        "name": "",
        "type": "bool"
      }
    ],
    "stateMutability": "view",
    "type": "function"
  },
  {
    "inputs": [],
    "name": "version",
    "outputs": [
      {
        "internalType": "string",
        "name": "",
        "type": "string"
      }
    ],
    "stateMutability": "pure",
    "type": "function"
  }
]
